caldav-stubs/METADATA.toml
caldav-stubs/__init__.pyi
caldav-stubs/davclient.pyi
caldav-stubs/objects.pyi
caldav-stubs/py.typed
caldav-stubs/requests.pyi
caldav-stubs/elements/__init__.pyi
caldav-stubs/elements/base.pyi
caldav-stubs/elements/cdav.pyi
caldav-stubs/elements/dav.pyi
caldav-stubs/elements/ical.pyi
caldav-stubs/lib/__init__.pyi
caldav-stubs/lib/error.pyi
caldav-stubs/lib/namespace.pyi
caldav-stubs/lib/url.pyi
caldav-stubs/lib/vcal.pyi
types_caldav-1.3.0.20241107.dist-info/METADATA
types_caldav-1.3.0.20241107.dist-info/WHEEL
types_caldav-1.3.0.20241107.dist-info/top_level.txt
types_caldav-1.3.0.20241107.dist-info/RECORD
